.gitignore
MANIFEST.in
README.rst
setup.py
cs/__init__.py
cs.commenteditor.egg-info/PKG-INFO
cs.commenteditor.egg-info/SOURCES.txt
cs.commenteditor.egg-info/dependency_links.txt
cs.commenteditor.egg-info/entry_points.txt
cs.commenteditor.egg-info/namespace_packages.txt
cs.commenteditor.egg-info/not-zip-safe
cs.commenteditor.egg-info/requires.txt
cs.commenteditor.egg-info/top_level.txt
cs/commenteditor/__init__.py
cs/commenteditor/browser.py
cs/commenteditor/configure.zcml
cs/commenteditor/rebuild_i18n.sh
cs/commenteditor/tests.py
cs/commenteditor/locales/cs.commenteditor-manual.pot
cs/commenteditor/locales/cs.commenteditor.pot
cs/commenteditor/locales/es/LC_MESSAGES/README.txt
cs/commenteditor/locales/es/LC_MESSAGES/cs.commenteditor.po
cs/commenteditor/locales/eu/LC_MESSAGES/README.txt
cs/commenteditor/locales/eu/LC_MESSAGES/cs.commenteditor.po
docs/HISTORY.txt
docs/INSTALL.txt
docs/LICENSE.GPL
docs/LICENSE.txt