Metadata-Version: 1.1
Name: cs.commenteditor
Version: 1.1.1
Summary: A view to edit comments created with plone.app.discussion
Home-page: http://github.com/codesyntax/cs.commenteditor
Author: Mikel Larreategi
Author-email: mlarreategi@codesyntax.com
License: GPL
Keywords: discussion edit comments
Platform: UNKNOWN
Classifier: Framework :: Plone
Classifier: Programming Language :: Python
